emulchem/__init__.py
emulchem/emulchem.py
emulchem/network.py
emulchem/data/chem/minMaxScaler.p
emulchem/data/chem/networkC
emulchem/data/chem/networkC+
emulchem/data/chem/networkC2
emulchem/data/chem/networkC2+
emulchem/data/chem/networkC2H
emulchem/data/chem/networkC2H+
emulchem/data/chem/networkC2H2
emulchem/data/chem/networkC2H2+
emulchem/data/chem/networkC2H3
emulchem/data/chem/networkC2H4
emulchem/data/chem/networkC2H5
emulchem/data/chem/networkC2H5OH
emulchem/data/chem/networkC2H5OH2+
emulchem/data/chem/networkC2N
emulchem/data/chem/networkC2N+
emulchem/data/chem/networkC2N2+
emulchem/data/chem/networkC2NH+
emulchem/data/chem/networkC3+
emulchem/data/chem/networkC3H2
emulchem/data/chem/networkC3H5+
emulchem/data/chem/networkC3N
emulchem/data/chem/networkC4H
emulchem/data/chem/networkC4N
emulchem/data/chem/networkC4N+
emulchem/data/chem/networkCH
emulchem/data/chem/networkCH+
emulchem/data/chem/networkCH2
emulchem/data/chem/networkCH2+
emulchem/data/chem/networkCH2CO
emulchem/data/chem/networkCH3
emulchem/data/chem/networkCH3+
emulchem/data/chem/networkCH3CCH
emulchem/data/chem/networkCH3CN
emulchem/data/chem/networkCH3CNH
emulchem/data/chem/networkCH3CNH+
emulchem/data/chem/networkCH3OH
emulchem/data/chem/networkCH3OH2+
emulchem/data/chem/networkCH4
emulchem/data/chem/networkCH4+
emulchem/data/chem/networkCH5+
emulchem/data/chem/networkCL
emulchem/data/chem/networkCL+
emulchem/data/chem/networkCN
emulchem/data/chem/networkCN+
emulchem/data/chem/networkCO
emulchem/data/chem/networkCO+
emulchem/data/chem/networkCO2
emulchem/data/chem/networkCS
emulchem/data/chem/networkCS+
emulchem/data/chem/networkH
emulchem/data/chem/networkH+
emulchem/data/chem/networkH2
emulchem/data/chem/networkH2+
emulchem/data/chem/networkH2CL+
emulchem/data/chem/networkH2CN
emulchem/data/chem/networkH2CO
emulchem/data/chem/networkH2CO+
emulchem/data/chem/networkH2CS
emulchem/data/chem/networkH2CS+
emulchem/data/chem/networkH2NO+
emulchem/data/chem/networkH2O
emulchem-0.1.0.dist-info/AUTHORS.rst
emulchem-0.1.0.dist-info/LICENSE
emulchem-0.1.0.dist-info/METADATA
emulchem-0.1.0.dist-info/WHEEL
emulchem-0.1.0.dist-info/top_level.txt
emulchem-0.1.0.dist-info/RECORD
