Metadata-Version: 2.1
Name: emulchem
Version: 0.1.0
Summary: A statistical emulator built using neural networks of the UCLCHEM and RADEX astronomical codes
Home-page: https://github.com/drd13/emulchem
Author: Damien de Mijolla
Author-email: ucapdde@ucl.ac.uk
License: MIT license
Keywords: emulchem
Platform: UNKNOWN
Classifier: Development Status :: 2 - Pre-Alpha
Classifier: Intended Audience :: Science/Research
Classifier: License :: OSI Approved :: MIT License
Classifier: Natural Language :: English
Classifier: Programming Language :: Python :: 2
Classifier: Programming Language :: Python :: 2.7
Classifier: Programming Language :: Python :: 3
Classifier: Programming Language :: Python :: 3.4
Classifier: Programming Language :: Python :: 3.5
Classifier: Programming Language :: Python :: 3.6
Classifier: Programming Language :: Python :: 3.7
Requires-Dist: numpy
